weightie/__init__.py
weightie/downloader.py
weightie/py.typed
weightie/serialiser.py
weightie-0.0.1.dist-info/LICENSE
weightie-0.0.1.dist-info/METADATA
weightie-0.0.1.dist-info/WHEEL
weightie-0.0.1.dist-info/top_level.txt
weightie-0.0.1.dist-info/RECORD
