Metadata-Version: 2.1
Name: weightie
Version: 0.0.1
Summary: Utility library for downloading and (de)serialising model weights for my little deep learning projects.
License: GNU GENERAL PUBLIC LICENSE
License-File: LICENSE
Requires-Dist: numpy
Requires-Dist: requests
Requires-Dist: platformdirs
